{"version":1,"resource":"vscode-remote://wsl%2Bubuntu/home/julien/umgestallten/script.sh","entries":[{"id":"YPdX.sh","timestamp":1649341483850},{"id":"i2HG.sh","source":"undoRedo.source","timestamp":1649342754920},{"id":"M1fn.sh","timestamp":1649342982010},{"id":"jFHF.sh","timestamp":1649343101340},{"id":"iBnx.sh","timestamp":1649343512470},{"id":"1wgi.sh","timestamp":1649343551330},{"id":"JsR1.sh","timestamp":1649343652530},{"id":"0tiQ.sh","timestamp":1649343763620},{"id":"SAdP.sh","timestamp":1649343800710},{"id":"NBAf.sh","timestamp":1649343850050},{"id":"Yi1U.sh","timestamp":1649343870830},{"id":"4Fy2.sh","timestamp":1649344292960},{"id":"Ri8Y.sh","timestamp":1649344438080},{"id":"ZUEi.sh","timestamp":1649345229810},{"id":"KctY.sh","timestamp":1649345730660}]}